solid/__init__.py
solid/examples/__init__.py
solid/examples/animation_example.py
solid/examples/append_solidpython_code.py
solid/examples/basic_geometry.py
solid/examples/basic_scad_include.py
solid/examples/bom_scad.py
solid/examples/hole_example.py
solid/examples/koch.py
solid/examples/mazebox/__init__.py
solid/examples/mazebox/inset.py
solid/examples/mazebox/maze7.png
solid/examples/mazebox/mazebox.py
solid/examples/mazebox/trianglemath.py
solid/examples/path_extrude_example.py
solid/examples/run_all_examples.sh
solid/examples/scad_to_include.scad
solid/examples/screw_thread_example.py
solid/examples/sierpinski.py
solid/examples/solidpython_template.py
solid/examples/splines_example.py
solid/extrude_along_path.py
solid/mypy/mypy_test.py
solid/objects.py
solid/patch_euclid.py
solid/py_scadparser/LICENSE
solid/py_scadparser/README.md
solid/py_scadparser/parsetab.py
solid/py_scadparser/scad_ast.py
solid/py_scadparser/scad_parser.py
solid/py_scadparser/scad_tokens.py
solid/screw_thread.py
solid/solidpython.py
solid/splines.py
solid/test/ExpandedTestCase.py
solid/test/__init__.py
solid/test/run_all_tests.sh
solid/test/solidpython.egg-info/PKG-INFO
solid/test/solidpython.egg-info/SOURCES.txt
solid/test/solidpython.egg-info/dependency_links.txt
solid/test/solidpython.egg-info/top_level.txt
solid/test/test_extrude_along_path.py
solid/test/test_screw_thread.py
solid/test/test_solidpython.py
solid/test/test_splines.py
solid/test/test_utils.py
solid/utils.py
solidpython-1.1.2.dist-info/WHEEL
solidpython-1.1.2.dist-info/METADATA
solidpython-1.1.2.dist-info/RECORD
